miller/__init__.py
miller/acquire.py
miller/catalog.py
miller/check.py
miller/examiners.py
miller/identify.py
miller/label.py
miller/rules.py
miller-0.1.8.dist-info/LICENSE
miller-0.1.8.dist-info/WHEEL
miller-0.1.8.dist-info/METADATA
miller-0.1.8.dist-info/RECORD
