Metadata-Version: 2.1
Name: miller
Version: 0.1.8
Summary: introspection tools using consistent, accessible syntax
Home-page: https://github.com/WithPrecedent/miller
License: Apache-2.0
Author: Corey Rayburn Yung
Author-email: coreyrayburnyung@gmail.com
Requires-Python: >=3.9,<4.0
Classifier: License :: OSI Approved :: Apache Software License
Classifier: Programming Language :: Python :: 3
Classifier: Programming Language :: Python :: 3.9
Classifier: Programming Language :: Python :: 3.10
Requires-Dist: camina (>=0.1.15,<0.2.0)
Requires-Dist: nagata (>=0.1.5,<0.2.0)
Project-URL: Repository, https://github.com/WithPrecedent/miller
